esg_lib/__init__.py
esg_lib/decorators.py
esg_lib/dto.py
esg_lib/paginator.py
esg_lib/utils.py
esg_lib/audit_logger/__init__.py
esg_lib/audit_logger/audit_logger_module.py
esg_lib/audit_logger/mongo_db.py
esg_lib/audit_logger/utils.py
esg_lib-0.1.dist-info/LICENSE
esg_lib-0.1.dist-info/METADATA
esg_lib-0.1.dist-info/WHEEL
esg_lib-0.1.dist-info/top_level.txt
esg_lib-0.1.dist-info/RECORD
