Metadata-Version: 2.1
Name: esg-lib
Version: 0.1
Summary: ESG Global Library
Home-page: UNKNOWN
Author: Myrza Nurmanbetov
Author-email: hakedhacked0@gmail.com
License: UNKNOWN
Platform: UNKNOWN
Classifier: Programming Language :: Python :: 3
Classifier: License :: OSI Approved :: MIT License
Classifier: Operating System :: OS Independent
Requires-Python: >=3.6
